frites/__init__.py
frites/config.py
frites/conn/__init__.py
frites/conn/conn_ccf.py
frites/conn/conn_covgc.py
frites/conn/conn_dfc.py
frites/conn/conn_fcd_corr.py
frites/conn/conn_fit.py
frites/conn/conn_ii.py
frites/conn/conn_io.py
frites/conn/conn_pid.py
frites/conn/conn_sliding_windows.py
frites/conn/conn_spec.py
frites/conn/conn_te.py
frites/conn/conn_tf.py
frites/conn/conn_utils.py
frites/core/__init__.py
frites/core/copnorm.py
frites/core/gcmi_1d.py
frites/core/gcmi_nd.py
frites/core/mi_bin_ephy.py
frites/data/frites.mplstyle
frites/dataset/__init__.py
frites/dataset/ds_ephy.py
frites/dataset/ds_utils.py
frites/dataset/suj_ephy.py
frites/estimator/__init__.py
frites/estimator/est_bin.py
frites/estimator/est_corr.py
frites/estimator/est_custom.py
frites/estimator/est_dcorr.py
frites/estimator/est_gcmi.py
frites/estimator/est_mi_base.py
frites/estimator/est_resampling.py
frites/io/__init__.py
frites/io/io_attributes.py
frites/io/io_dependencies.py
frites/io/io_syslog.py
frites/plot/__init__.py
frites/plot/plot_conn.py
frites/simulations/__init__.py
frites/simulations/sim_ar.py
frites/simulations/sim_generate_data.py
frites/simulations/sim_local_mi.py
frites/simulations/sim_mi.py
frites/stats/__init__.py
frites/stats/stats_mcp.py
frites/stats/stats_nonparam.py
frites/stats/stats_param.py
frites/utils/__init__.py
frites/utils/parallel.py
frites/utils/perf.py
frites/utils/preproc.py
frites/utils/wrapper.py
frites/workflow/__init__.py
frites/workflow/wf_base.py
frites/workflow/wf_conn_comod.py
frites/workflow/wf_mi.py
frites/workflow/wf_mi_combine.py
frites/workflow/wf_stats.py
frites-0.4.4.dist-info/LICENSE
frites-0.4.4.dist-info/METADATA
frites-0.4.4.dist-info/WHEEL
frites-0.4.4.dist-info/top_level.txt
frites-0.4.4.dist-info/RECORD
