Metadata-Version: 2.1
Name: frites
Version: 0.4.4
Summary: Framework of Information Theory for Electrophysiological data and Statistics
Home-page: https://github.com/brainets/frites
Download-URL: https://github.com/brainets/frites/archive/v0.4.4.tar.gz
Author: BraiNets
Author-email: e.combrisson@gmail.com
Maintainer: Etienne Combrisson
License: BSD 3-Clause License
Keywords: information-theory statistics
Platform: any
Classifier: Development Status :: 5 - Production/Stable
Classifier: Intended Audience :: Science/Research
Classifier: Intended Audience :: Education
Classifier: Intended Audience :: Developers
Classifier: Programming Language :: Python :: 3.8
Classifier: Programming Language :: Python :: 3.9
Classifier: Programming Language :: Python :: 3.10
Classifier: Programming Language :: Python :: 3.11
License-File: LICENSE
Requires-Dist: numpy
Requires-Dist: scipy
Requires-Dist: mne
Requires-Dist: joblib
Requires-Dist: xarray
Requires-Dist: netCDF4
Requires-Dist: h5netcdf
Requires-Dist: scikit-learn
Provides-Extra: all
Requires-Dist: matplotlib ; extra == 'all'
Requires-Dist: networkx ; extra == 'all'
Requires-Dist: numba ; extra == 'all'
Requires-Dist: dcor ; extra == 'all'
Provides-Extra: doc
Requires-Dist: matplotlib ; extra == 'doc'
Requires-Dist: networkx ; extra == 'doc'
Requires-Dist: numba ; extra == 'doc'
Requires-Dist: dcor ; extra == 'doc'
Requires-Dist: pytest ; extra == 'doc'
Requires-Dist: pytest-sugar ; extra == 'doc'
Requires-Dist: pytest-cov ; extra == 'doc'
Requires-Dist: codecov ; extra == 'doc'
Requires-Dist: sphinx (!=4.1.0) ; extra == 'doc'
Requires-Dist: sphinx-gallery ; extra == 'doc'
Requires-Dist: pydata-sphinx-theme (>=0.6.3) ; extra == 'doc'
Requires-Dist: sphinxcontrib-bibtex (==1.0.0) ; extra == 'doc'
Requires-Dist: numpydoc ; extra == 'doc'
Requires-Dist: xlrd ; extra == 'doc'
Requires-Dist: openpyxl ; extra == 'doc'
Requires-Dist: seaborn ; extra == 'doc'
Requires-Dist: memory-profiler ; extra == 'doc'
Requires-Dist: sphinx-panels ; extra == 'doc'
Requires-Dist: sphinx-copybutton ; extra == 'doc'
Provides-Extra: flake
Requires-Dist: matplotlib ; extra == 'flake'
Requires-Dist: networkx ; extra == 'flake'
Requires-Dist: numba ; extra == 'flake'
Requires-Dist: dcor ; extra == 'flake'
Requires-Dist: pytest ; extra == 'flake'
Requires-Dist: pytest-sugar ; extra == 'flake'
Requires-Dist: pytest-cov ; extra == 'flake'
Requires-Dist: codecov ; extra == 'flake'
Requires-Dist: flake8 ; extra == 'flake'
Requires-Dist: pep8-naming ; extra == 'flake'
Provides-Extra: full
Requires-Dist: matplotlib ; extra == 'full'
Requires-Dist: networkx ; extra == 'full'
Requires-Dist: numba ; extra == 'full'
Requires-Dist: dcor ; extra == 'full'
Requires-Dist: pytest ; extra == 'full'
Requires-Dist: pytest-sugar ; extra == 'full'
Requires-Dist: pytest-cov ; extra == 'full'
Requires-Dist: codecov ; extra == 'full'
Requires-Dist: sphinx (!=4.1.0) ; extra == 'full'
Requires-Dist: sphinx-gallery ; extra == 'full'
Requires-Dist: pydata-sphinx-theme (>=0.6.3) ; extra == 'full'
Requires-Dist: sphinxcontrib-bibtex (==1.0.0) ; extra == 'full'
Requires-Dist: numpydoc ; extra == 'full'
Requires-Dist: xlrd ; extra == 'full'
Requires-Dist: openpyxl ; extra == 'full'
Requires-Dist: seaborn ; extra == 'full'
Requires-Dist: memory-profiler ; extra == 'full'
Requires-Dist: sphinx-panels ; extra == 'full'
Requires-Dist: sphinx-copybutton ; extra == 'full'
Requires-Dist: flake8 ; extra == 'full'
Requires-Dist: pep8-naming ; extra == 'full'
Provides-Extra: test
Requires-Dist: matplotlib ; extra == 'test'
Requires-Dist: networkx ; extra == 'test'
Requires-Dist: numba ; extra == 'test'
Requires-Dist: dcor ; extra == 'test'
Requires-Dist: pytest ; extra == 'test'
Requires-Dist: pytest-sugar ; extra == 'test'
Requires-Dist: pytest-cov ; extra == 'test'
Requires-Dist: codecov ; extra == 'test'
